fostool/__init__.py
fostool/pipeline.py
fostool/config/__init__.py
fostool/config/default.yaml
fostool/dataset/__init__.py
fostool/dataset/data_utils.py
fostool/model/__init__.py
fostool/model/gcn.py
fostool/model/gconv.py
fostool/model/input_fixer.py
fostool/model/krnn.py
fostool/model/mlp.py
fostool/model/sandwich.py
fostool/task/__init__.py
fostool/task/config_handler.py
fostool/task/fusion.py
fostool/task/logger.py
fostool/task/loss.py
fostool/tools/__init__.py
fostool/tools/predictor.py
fostool/tools/trainer.py
fostool/tools/utils.py
fostool/visualizer/__init__.py
fostool/visualizer/plot.py
fostool-0.0.4.dist-info/LICENSE
fostool-0.0.4.dist-info/METADATA
fostool-0.0.4.dist-info/WHEEL
fostool-0.0.4.dist-info/top_level.txt
fostool-0.0.4.dist-info/RECORD
