Metadata-Version: 2.1
Name: fostool
Version: 0.0.4
Summary: FOST Python Package
Home-page: https://github.com/microsoft/FOST
Author: Microsoft
Author-email: fostool@microsoft.com
License: The MIT License (Microsoft)
Platform: UNKNOWN
License-File: LICENSE
Requires-Dist: scikit-learn
Requires-Dist: matplotlib
Requires-Dist: numpy
Requires-Dist: pandas
Requires-Dist: pyyaml (>=5.1)
Requires-Dist: addict
